LICENSE.txt
MANIFEST.in
README.rst
requirements.txt
setup.py
word2number/__init__.py
word2number/w2n.py
word2number.egg-info/PKG-INFO
word2number.egg-info/SOURCES.txt
word2number.egg-info/dependency_links.txt
word2number.egg-info/top_level.txt