Metadata-Version: 1.1
Name: word2number
Version: 1.0
Summary: Convert number words eg. three hundred and forty two to numbers (342).
Home-page: https://github.com/akshaynagpal/w2n
Author: Akshay Nagpal
Author-email: akshay2626@gmail.com
License: The MIT License (MIT)
